text_forge/__init__.py
text_forge/build.py
text_forge/cli.py
text_forge/plugin.py
sg_text_forge-0.1.5.data/data/share/text-forge/epub/book_meta.yml
sg_text_forge-0.1.5.data/data/share/text-forge/epub/epub.css
sg_text_forge-0.1.5.data/data/share/text-forge/scripts/mkdocs-combine.py
sg_text_forge-0.1.5.data/data/share/text-forge/scripts/process-epub-meta.py
sg_text_forge-0.1.5.data/data/share/text-forge/scripts/pymdown-pandoc.lua
sg_text_forge-0.1.5.data/data/share/text-forge/scripts/fixtures/ptn_lua_admonition.md
sg_text_forge-0.1.5.data/data/share/text-forge/scripts/fixtures/ptn_lua_image.md
sg_text_forge-0.1.5.data/data/share/text-forge/mkdocs/hooks/nobr_emoticons.py
sg_text_forge-0.1.5.data/data/share/text-forge/mkdocs/overrides/main.html
sg_text_forge-0.1.5.data/data/share/text-forge/mkdocs/overrides/assets/js/editor.js
sg_text_forge-0.1.5.data/data/share/text-forge/mkdocs/overrides/assets/js/translations.json
sg_text_forge-0.1.5.data/data/share/text-forge/mkdocs/overrides/assets/stylesheets/editor.css
sg_text_forge-0.1.5.data/data/share/text-forge/mkdocs/overrides/assets/stylesheets/text-forge.css
sg_text_forge-0.1.5.data/data/share/text-forge/mkdocs/overrides/partials/comments.html
sg_text_forge-0.1.5.data/data/share/text-forge/mkdocs/overrides/partials/downloads.html
sg_text_forge-0.1.5.data/data/share/text-forge/mkdocs/overrides/partials/editor.html
sg_text_forge-0.1.5.data/data/share/text-forge/mkdocs/overrides/partials/header.html
sg_text_forge-0.1.5.data/data/share/text-forge/mkdocs/overrides/partials/source-file.html
sg_text_forge-0.1.5.dist-info/METADATA
sg_text_forge-0.1.5.dist-info/WHEEL
sg_text_forge-0.1.5.dist-info/entry_points.txt
sg_text_forge-0.1.5.dist-info/licenses/LICENSE
sg_text_forge-0.1.5.dist-info/RECORD
