Metadata-Version: 2.4
Name: sg-text-forge
Version: 0.1.5
Summary: MkDocs plugin and build pipeline for Markdown text projects with EPUB generation
Project-URL: Homepage, https://github.com/shared-goals/text-forge
Project-URL: Repository, https://github.com/shared-goals/text-forge
Project-URL: Issues, https://github.com/shared-goals/text-forge/issues
Project-URL: Documentation, https://github.com/shared-goals/text-forge#readme
Author-email: Bongiozzo <sergey.polyakov@hotmail.com>
Maintainer-email: Bongiozzo <sergey.polyakov@hotmail.com>
License: MIT
License-File: LICENSE
Keywords: documentation,epub,markdown,mkdocs,mkdocs-plugin,publishing
Classifier: Development Status :: 4 - Beta
Classifier: Intended Audience :: Developers
Classifier: License :: OSI Approved :: MIT License
Classifier: Programming Language :: Python :: 3
Classifier: Programming Language :: Python :: 3.11
Classifier: Programming Language :: Python :: 3.12
Classifier: Topic :: Documentation
Classifier: Topic :: Software Development :: Documentation
Classifier: Topic :: Text Processing :: Markup :: Markdown
Requires-Python: >=3.11
Requires-Dist: click<8.2.2,>=8.1.7
Requires-Dist: livereload>=2.7.1
Requires-Dist: mkdocs-git-committers-plugin-2>=2.5.0
Requires-Dist: mkdocs-git-revision-date-localized-plugin>=1.5.0
Requires-Dist: mkdocs-material>=9.6.22
Requires-Dist: mkdocs>=1.6.1
Requires-Dist: pyyaml>=6.0.3
